global_permissions/__init__.py
global_permissions/admin.py
global_permissions/models.py
global_permissions/migrations/0001_initial.py
global_permissions/migrations/__init__.py
django_global_permissions-0.2.6.dist-info/AUTHORS.md
django_global_permissions-0.2.6.dist-info/LICENSE
django_global_permissions-0.2.6.dist-info/METADATA
django_global_permissions-0.2.6.dist-info/WHEEL
django_global_permissions-0.2.6.dist-info/top_level.txt
django_global_permissions-0.2.6.dist-info/RECORD
