Metadata-Version: 2.1
Name: django-global-permissions
Version: 0.2.6
Summary: Implementation of permissions not related to models
Home-page: https://github.com/eduardo-matos/django-global-permissions
Author: Eduardo Matos
Author-email: eduardo.matos.silva@gmail.com
License: BSD
Keywords: django-global-permissions
Platform: UNKNOWN
Classifier: Development Status :: 4 - Beta
Classifier: Framework :: Django
Classifier: Intended Audience :: Developers
Classifier: License :: OSI Approved :: BSD License
Classifier: Natural Language :: English
Classifier: Programming Language :: Python :: 2
Classifier: Programming Language :: Python :: 2.6
Classifier: Programming Language :: Python :: 2.7
Classifier: Programming Language :: Python :: 3
Classifier: Programming Language :: Python :: 3.3
Classifier: Programming Language :: Python :: 3.4
Classifier: Programming Language :: Python :: 3.5
Classifier: Programming Language :: Python :: 3.8
Classifier: Programming Language :: Python :: 3.9
License-File: LICENSE
License-File: AUTHORS.md
Requires-Dist: django (>=1.4)
